roysh/__init__.py
roysh/shell.py
roysh-0.1.dist-info/METADATA
roysh-0.1.dist-info/WHEEL
roysh-0.1.dist-info/entry_points.txt
roysh-0.1.dist-info/top_level.txt
roysh-0.1.dist-info/RECORD
