Metadata-Version: 2.1
Name: roysh
Version: 0.1
Summary: A Python-based shell with tab completion
Home-page: https://github.com/nishanroy561/RoySH
Author: Nishan Roy
Author-email: nishanroy561@gmail.com
Classifier: Programming Language :: Python :: 3
Classifier: License :: OSI Approved :: MIT License
Classifier: Operating System :: OS Independent
Classifier: Environment :: Console
Classifier: Intended Audience :: Developers
Classifier: Topic :: System :: Shells
Requires-Python: >=3.6
Requires-Dist: pyreadline3
